nia_mcp_server/__init__.py
nia_mcp_server/__main__.py
nia_mcp_server/api_client.py
nia_mcp_server/cli.py
nia_mcp_server/profiles.py
nia_mcp_server/project_init.py
nia_mcp_server/rule_transformer.py
nia_mcp_server/server.py
nia_mcp_server/setup.py
nia_mcp_server/assets/rules/claude_rules.md
nia_mcp_server/assets/rules/cursor_rules.md
nia_mcp_server/assets/rules/nia_rules.md
nia_mcp_server/assets/rules/vscode_rules.md
nia_mcp_server/assets/rules/windsurf_rules.md
nia_mcp_server-1.0.79.dist-info/METADATA
nia_mcp_server-1.0.79.dist-info/WHEEL
nia_mcp_server-1.0.79.dist-info/entry_points.txt
nia_mcp_server-1.0.79.dist-info/licenses/LICENSE
nia_mcp_server-1.0.79.dist-info/RECORD
